sbrscrape/__init__.py
sbrscrape-0.0.10.dist-info/LICENSE
sbrscrape-0.0.10.dist-info/METADATA
sbrscrape-0.0.10.dist-info/WHEEL
sbrscrape-0.0.10.dist-info/top_level.txt
sbrscrape-0.0.10.dist-info/RECORD
