Metadata-Version: 2.1
Name: sbrscrape
Version: 0.0.10
Summary: Scrape odds data from sbrodds
Author-email: Nolan Gilley <nkgilley@gmail.com>
Project-URL: Homepage, https://github.com/nkgilley/sbrscrape
Project-URL: Bug Tracker, https://github.com/nkgilley/sbrscrape/issues
Classifier: Programming Language :: Python :: 3
Classifier: License :: OSI Approved :: MIT License
Classifier: Operating System :: OS Independent
Requires-Python: >=3.5
License-File: LICENSE
